qyet/__init__.py
qyet-0.1.2.dist-info/LICENSE
qyet-0.1.2.dist-info/METADATA
qyet-0.1.2.dist-info/WHEEL
qyet-0.1.2.dist-info/RECORD
