Metadata-Version: 2.1
Name: qyet
Version: 0.1.2
Summary: 
Author: Vitor Buxbaum
Author-email: vitorbuxbaum@gmail.com
Requires-Python: >=3.11,<4.0
Classifier: Development Status :: 5 - Production/Stable
Classifier: Programming Language :: Python :: 3
Classifier: Programming Language :: Python :: 3.11
Classifier: Programming Language :: Python :: 3
Classifier: Programming Language :: Python :: 3.11
Project-URL: Documentation, https://qyet.readthedocs.io/en/latest/
Project-URL: Repository, https://github.com/vbuxbaum/qyet
